{
    "streetNames": [
        "Karl Johans Gate",
        "Dronning Eufemias Gate",
        "Akersgata",
        "Torggata",
        "Storgata",
        "Grensen",
        "Øvre Slottsgate",
        "Bislettgata",
        "Frognerveien",
        "Sørkedalsveien",
        "Kirkegata",
        "Rosenkrantz' Gate",
        "Bergenhusveien",
        "Tonsbergveien",
        "Solli Plass",
        "Nygata",
        "Østervoldgata",
        "Lille Grensen",
        "Jernbanetorget",
        "Hammersborggata"
    ],
    "streetNumbers": [
        "101",
        "202",
        "303",
        "404",
        "505",
        "606",
        "707",
        "808",
        "909",
        "1234",
        "4321",
        "5678",
        "6789",
        "7890",
        "8901",
        "2345",
        "3456",
        "4567",
        "5670",
        "6781"
    ],
    "cities": [
        "Oslo",
        "Bergen",
        "Stavanger",
        "Drammen",
        "Trondheim",
        "Kristiansand",
        "Fredrikstad",
        "Düden",
        "Haugesund",
        "Sandnes",
        "Tromsø",
        "Bodø",
        "Moss",
        "Larvik",
        "Skien",
        "Arendal",
        "Porsgrunn",
        "Hamar",
        "Gjøvik",
        "Kongsberg"
    ],
    "states": [
        "Oslo",
        "Viken",
        "Vestland",
        "Agder",
        "Rogaland",
        "Trøndelag",
        "Møre og Romsdal",
        "Nordland",
        "Innlandet",
        "Troms og Finnmark"
    ],
    "zipCodes": [
        "0151",
        "5000",
        "7011",
        "6001",
        "9000",
        "0101",
        "1600",
        "3200",
        "9001",
        "3000",
        "1000",
        "2000",
        "7000",
        "4000",
        "8000",
        "1300",
        "2500",
        "2900",
        "0800",
        "2400"
    ]
}